passagemath_graphs/__init__.py
passagemath_graphs-10.6.47.dist-info/DELVEWHEEL
passagemath_graphs-10.6.47.dist-info/METADATA
passagemath_graphs-10.6.47.dist-info/RECORD
passagemath_graphs-10.6.47.dist-info/top_level.txt
passagemath_graphs-10.6.47.dist-info/WHEEL
passagemath_graphs.libs/libgmp-10-6a8fe126122672a8aed2558e30454e74.dll
passagemath_graphs.libs/msvcp140-a4c2229bdc2a2a630acdc095b4d86008.dll
sage/all__sagemath_graphs.py
sage/combinat/abstract_tree.py
sage/combinat/all__sagemath_graphs.py
sage/combinat/binary_tree.py
sage/combinat/finite_state_machine.py
sage/combinat/finite_state_machine_generators.py
sage/combinat/graph_path.py
sage/combinat/interval_posets.py
sage/combinat/nu_tamari_lattice.py
sage/combinat/ordered_tree.py
sage/combinat/rooted_tree.py
sage/combinat/shard_order.py
sage/combinat/tamari_lattices.py
sage/combinat/yang_baxter_graph.py
sage/combinat/cluster_algebra_quiver/all.py
sage/combinat/cluster_algebra_quiver/cluster_seed.py
sage/combinat/cluster_algebra_quiver/interact.py
sage/combinat/cluster_algebra_quiver/mutation_class.py
sage/combinat/cluster_algebra_quiver/mutation_type.py
sage/combinat/cluster_algebra_quiver/quiver.py
sage/combinat/cluster_algebra_quiver/quiver_mutation_type.py
sage/combinat/designs/all.py
sage/combinat/designs/bibd.py
sage/combinat/designs/block_design.py
sage/combinat/designs/covering_array.py
sage/combinat/designs/covering_design.py
sage/combinat/designs/database.py
sage/combinat/designs/designs_pyx.cp310-win_amd64.pyd
sage/combinat/designs/designs_pyx.pxd
sage/combinat/designs/designs_pyx.pyx
sage/combinat/designs/design_catalog.py
sage/combinat/designs/difference_family.py
sage/combinat/designs/difference_matrices.py
sage/combinat/designs/evenly_distributed_sets.cp310-win_amd64.pyd
sage/combinat/designs/evenly_distributed_sets.pyx
sage/combinat/designs/ext_rep.py
sage/combinat/designs/gen_quadrangles_with_spread.cp310-win_amd64.pyd
sage/combinat/designs/gen_quadrangles_with_spread.pyx
sage/combinat/designs/group_divisible_designs.py
sage/combinat/designs/incidence_structures.py
sage/combinat/designs/latin_squares.py
sage/combinat/designs/MOLS_handbook_data.py
sage/combinat/designs/orthogonal_arrays.py
