Metadata-Version: 2.4
Name: passagemath-graphs
Version: 10.6.47
Summary: passagemath: Graphs, posets, hypergraphs, designs, abstract complexes, combinatorial polyhedra, abelian sandpiles, quivers
Author-email: The Sage Developers <sage-support@googlegroups.com>
Maintainer: Matthias Köppe, passagemath contributors
License-Expression: GPL-2.0-or-later
Project-URL: release notes, https://github.com/passagemath/passagemath/releases
Project-URL: repo (upstream), https://github.com/sagemath/sage
Project-URL: repo, https://github.com/passagemath/passagemath
Project-URL: documentation, https://passagemath.org/docs/latest
Project-URL: homepage (upstream), https://www.sagemath.org
Project-URL: discourse, https://passagemath.discourse.group
Project-URL: tracker (upstream), https://github.com/sagemath/sage/issues
Project-URL: tracker, https://github.com/passagemath/passagemath/issues
Classifier: Development Status :: 6 - Mature
Classifier: Intended Audience :: Education
Classifier: Intended Audience :: Science/Research
Classifier: Operating System :: POSIX
Classifier: Operating System :: POSIX :: Linux
Classifier: Operating System :: MacOS :: MacOS X
Classifier: Operating System :: Microsoft :: Windows
Classifier: Programming Language :: Python :: 3 :: Only
Classifier: Programming Language :: Python :: 3.10
Classifier: Programming Language :: Python :: 3.11
Classifier: Programming Language :: Python :: 3.12
Classifier: Programming Language :: Python :: 3.13
Classifier: Programming Language :: Python :: 3.14
Classifier: Programming Language :: Python :: Implementation :: CPython
Classifier: Topic :: Scientific/Engineering :: Mathematics
Requires-Python: <3.15,>=3.10
Requires-Dist: gmpy2~=2.1.b999
Requires-Dist: cysignals!=1.12.4; sys_platform == "win32"
Requires-Dist: cysignals!=1.12.0,>=1.11.2
Requires-Dist: memory_allocator
Requires-Dist: passagemath-categories~=10.6.47.0
Requires-Dist: passagemath-conf~=10.6.47.0; sys_platform != "win32"
Requires-Dist: passagemath-environment~=10.6.47.0
Provides-Extra: test
Requires-Dist: passagemath-repl; extra == "test"
Provides-Extra: benzene
Requires-Dist: passagemath-benzene; extra == "benzene"
Provides-Extra: bliss
Requires-Dist: passagemath-bliss; extra == "bliss"
Provides-Extra: buckygen
Requires-Dist: passagemath-buckygen; extra == "buckygen"
Provides-Extra: cliquer
Requires-Dist: passagemath-cliquer; extra == "cliquer"
Provides-Extra: cmr
Requires-Dist: passagemath-cmr; extra == "cmr"
Provides-Extra: gap
Requires-Dist: passagemath-gap; extra == "gap"
Provides-Extra: igraph
Requires-Dist: igraph; extra == "igraph"
Provides-Extra: mcqd
Requires-Dist: passagemath-mcqd; extra == "mcqd"
Provides-Extra: nauty
Requires-Dist: passagemath-nauty; extra == "nauty"
Provides-Extra: networkx
Requires-Dist: networkx>=2.4; extra == "networkx"
Provides-Extra: pari
Requires-Dist: passagemath-pari; extra == "pari"
Provides-Extra: planarity
Requires-Dist: passagemath-planarity; extra == "planarity"
Provides-Extra: plantri
Requires-Dist: passagemath-plantri; extra == "plantri"
Provides-Extra: rankwidth
Requires-Dist: passagemath-rankwidth; extra == "rankwidth"
Provides-Extra: rw
Requires-Dist: passagemath-graphs[rankwidth]; extra == "rw"
Provides-Extra: tdlib
Requires-Dist: passagemath-tdlib; extra == "tdlib"
Provides-Extra: combinat
Requires-Dist: passagemath-combinat; extra == "combinat"
Provides-Extra: databases
Provides-Extra: editor
Requires-Dist: phitigra>=0.2.6; extra == "editor"
Provides-Extra: groups
Requires-Dist: passagemath-groups; extra == "groups"
Requires-Dist: passagemath-graphs[nauty]; extra == "groups"
Provides-Extra: homology
Requires-Dist: passagemath-modules; extra == "homology"
Provides-Extra: mip
Requires-Dist: passagemath-polyhedra; extra == "mip"
Provides-Extra: modules
Requires-Dist: passagemath-modules; extra == "modules"
Provides-Extra: plot
Requires-Dist: passagemath-plot; extra == "plot"
Provides-Extra: polyhedra
Requires-Dist: passagemath-polyhedra; extra == "polyhedra"
Provides-Extra: repl
Requires-Dist: passagemath-repl; extra == "repl"
Provides-Extra: sat
Requires-Dist: passagemath-combinat; extra == "sat"
Provides-Extra: standard
Requires-Dist: passagemath-graphs[combinat,databases,groups,mip,modules,planarity,polyhedra,rankwidth,repl]; extra == "standard"
Requires-Dist: passagemath-plot[tachyon]; extra == "standard"
